azure_cost_analyzer.py
azure_cost_analyzer_cli-2.0.0.dist-info/licenses/LICENSE
azure_cost_analyzer_cli-2.0.0.dist-info/METADATA
azure_cost_analyzer_cli-2.0.0.dist-info/WHEEL
azure_cost_analyzer_cli-2.0.0.dist-info/entry_points.txt
azure_cost_analyzer_cli-2.0.0.dist-info/top_level.txt
azure_cost_analyzer_cli-2.0.0.dist-info/RECORD
