Metadata-Version: 2.4
Name: azure-cost-analyzer-cli
Version: 2.0.0
Summary: Enterprise Azure cost analysis tool with comprehensive reporting
Home-page: https://github.com/CodeVerdict/azure-cost-reporter
Author: Qanooni
Author-email: Qanooni <support@qanooni.com>
Maintainer-email: Qanooni <support@qanooni.com>
License: MIT
Project-URL: Homepage, https://github.com/CodeVerdict/azure-cost-reporter
Project-URL: Repository, https://github.com/CodeVerdict/azure-cost-reporter
Project-URL: Documentation, https://github.com/CodeVerdict/azure-cost-reporter#readme
Project-URL: Bug Reports, https://github.com/CodeVerdict/azure-cost-reporter/issues
Keywords: azure,cost,analysis,reporting,cloud,monitoring,finance,cli,enterprise,budget
Platform: any
Classifier: Development Status :: 5 - Production/Stable
Classifier: Intended Audience :: Developers
Classifier: Intended Audience :: System Administrators
Classifier: Intended Audience :: Financial and Insurance Industry
Classifier: Topic :: Office/Business :: Financial
Classifier: Topic :: System :: Monitoring
Classifier: Topic :: Utilities
Classifier: License :: OSI Approved :: MIT License
Classifier: Programming Language :: Python :: 3
Classifier: Programming Language :: Python :: 3.7
Classifier: Programming Language :: Python :: 3.8
Classifier: Programming Language :: Python :: 3.9
Classifier: Programming Language :: Python :: 3.10
Classifier: Programming Language :: Python :: 3.11
Classifier: Programming Language :: Python :: 3.12
Classifier: Operating System :: OS Independent
Classifier: Environment :: Console
Requires-Python: >=3.7
License-File: LICENSE
Requires-Dist: pandas>=1.3.0
Requires-Dist: matplotlib>=3.3.0
Requires-Dist: openpyxl>=3.0.0
Requires-Dist: seaborn>=0.11.0
Provides-Extra: dev
Requires-Dist: pytest>=6.0; extra == "dev"
Requires-Dist: pytest-cov>=2.0; extra == "dev"
Requires-Dist: black>=21.0; extra == "dev"
Requires-Dist: flake8>=3.8; extra == "dev"
Requires-Dist: mypy>=0.800; extra == "dev"
Dynamic: author
Dynamic: home-page
Dynamic: license-file
Dynamic: platform
Dynamic: requires-python
